kdl_ldap/__init__.py
kdl_ldap/apps.py
kdl_ldap/settings.py
kdl_ldap/signal_handlers.py
django_kdl_ldap-1.2.dist-info/LICENSE
django_kdl_ldap-1.2.dist-info/METADATA
django_kdl_ldap-1.2.dist-info/WHEEL
django_kdl_ldap-1.2.dist-info/top_level.txt
django_kdl_ldap-1.2.dist-info/RECORD
