Metadata-Version: 2.1
Name: django-kdl-ldap
Version: 1.2
Summary: Django LDAP authentication for KDL
Home-page: https://github.com/kingsdigitallab/django-kdl-ldap
Author: King's Digital Lab
Author-email: kdl-info@kcl.ac.uk
License: MIT
Keywords: django kdl ldap
Platform: UNKNOWN
Classifier: Development Status :: 5 - Production/Stable
Classifier: Framework :: Django
Classifier: Intended Audience :: Developers
Classifier: License :: OSI Approved :: MIT License
Classifier: Programming Language :: Python :: 2
Classifier: Programming Language :: Python :: 2.7
Classifier: Programming Language :: Python :: 3
Classifier: Programming Language :: Python :: 3.3
Classifier: Programming Language :: Python :: 3.4
Classifier: Programming Language :: Python :: 3.5
Classifier: Topic :: System :: Systems Administration :: Authentication/Directory :: LDAP
Classifier: Topic :: Utilities
Requires-Dist: django-auth-ldap
